my_ml_lib/MyAgglomerative.py
my_ml_lib/MyBoostClf.py
my_ml_lib/MyBoostReg.py
my_ml_lib/MyDBSCAN.py
my_ml_lib/MyForestClf.py
my_ml_lib/MyForestReg.py
my_ml_lib/MyKMeans.py
my_ml_lib/MyKNNClf.py
my_ml_lib/MyKNNReg.py
my_ml_lib/MyLineReg.py
my_ml_lib/MyLogReg.py
my_ml_lib/MyPCA.py
my_ml_lib/MySVM.py
my_ml_lib/MyTreeClf.py
my_ml_lib/MyTreeReg.py
my_ml_lib/__init__.py
my_ml_lib/base_distances.py
my_ml_lib/base_metrics.py
my_ml_lib/classification_metrics.py
my_ml_lib/clustering_metrics.py
my_ml_lib/distance_metrics.py
my_ml_lib/regression_metrics.py
my_ml_lib-0.1.0.dist-info/licenses/LICENSE
my_ml_lib-0.1.0.dist-info/METADATA
my_ml_lib-0.1.0.dist-info/WHEEL
my_ml_lib-0.1.0.dist-info/top_level.txt
my_ml_lib-0.1.0.dist-info/RECORD
