Metadata-Version: 2.4
Name: my-ml-lib
Version: 0.1.0
Summary: Machine learning library similar to scikit-learn
Author-email: Oleg Stekhun <stekhun@mail.ru>
License: MIT License
Requires-Python: >=3.8
License-File: LICENSE
Requires-Dist: numpy>=1.20
Requires-Dist: pandas>=1.3
Dynamic: license-file
